LICENSE.txt
README.md
awesome_exception/__init__.py
awesome_exception/exceptions/__init__.py
awesome_exception-1.1.0.dist-info/LICENSE.txt
awesome_exception-1.1.0.dist-info/WHEEL
awesome_exception-1.1.0.dist-info/METADATA
awesome_exception-1.1.0.dist-info/RECORD
